djangocms_icon/__init__.py
djangocms_icon/apps.py
djangocms_icon/cms_plugins.py
djangocms_icon/fields.py
djangocms_icon/forms.py
djangocms_icon/models.py
djangocms_icon/locale/de/LC_MESSAGES/django.mo
djangocms_icon/locale/de/LC_MESSAGES/django.po
djangocms_icon/locale/en/LC_MESSAGES/django.mo
djangocms_icon/locale/en/LC_MESSAGES/django.po
djangocms_icon/locale/es/LC_MESSAGES/django.mo
djangocms_icon/locale/es/LC_MESSAGES/django.po
djangocms_icon/locale/fr/LC_MESSAGES/django.mo
djangocms_icon/locale/fr/LC_MESSAGES/django.po
djangocms_icon/locale/it/LC_MESSAGES/django.mo
djangocms_icon/locale/it/LC_MESSAGES/django.po
djangocms_icon/migrations/0001_initial.py
djangocms_icon/migrations/0002_auto_20190218_2017.py
djangocms_icon/migrations/0003_alter_icon_cmsplugin_ptr.py
djangocms_icon/migrations/__init__.py
djangocms_icon/static/djangocms_icon/css/djangocms-icon.css
djangocms_icon/static/djangocms_icon/js/base.js
djangocms_icon/static/djangocms_icon/js/icon-picker.js
djangocms_icon/static/djangocms_icon/js/icon-widget.js
djangocms_icon/static/djangocms_icon/js/dist/bundle.icon.min.js
djangocms_icon/static/djangocms_icon/js/libs/bootstrap-iconpicker.js
djangocms_icon/static/djangocms_icon/js/libs/iconset/iconset-elusiveicon-all.js
djangocms_icon/static/djangocms_icon/js/libs/iconset/iconset-flagicon-all.js
djangocms_icon/static/djangocms_icon/js/libs/iconset/iconset-fontawesome-4-all.js
djangocms_icon/static/djangocms_icon/js/libs/iconset/iconset-fontawesome-5-brands.js
djangocms_icon/static/djangocms_icon/js/libs/iconset/iconset-fontawesome-5-light.js
djangocms_icon/static/djangocms_icon/js/libs/iconset/iconset-fontawesome-5-regular.js
djangocms_icon/static/djangocms_icon/js/libs/iconset/iconset-fontawesome-5-solid.js
djangocms_icon/static/djangocms_icon/js/libs/iconset/iconset-glyphicon-all.js
djangocms_icon/static/djangocms_icon/js/libs/iconset/iconset-ionicon-all.js
djangocms_icon/static/djangocms_icon/js/libs/iconset/iconset-mapicon-all.js
djangocms_icon-2.1.0.dist-info/LICENSE
djangocms_icon-2.1.0.dist-info/METADATA
djangocms_icon-2.1.0.dist-info/WHEEL
djangocms_icon-2.1.0.dist-info/top_level.txt
djangocms_icon-2.1.0.dist-info/RECORD
